mdx_google_map.py
mdx_google_map-1.0.1.dist-info/METADATA
mdx_google_map-1.0.1.dist-info/RECORD
mdx_google_map-1.0.1.dist-info/WHEEL
mdx_google_map-1.0.1.dist-info/top_level.txt
