Metadata-Version: 2.1
Name: mdx-google-map
Version: 1.0.1
Summary: A python Markdown extension providing Google Maps syntax
Home-page: https://github.com/tictocs/markdown-google-map/
Author: Tom Manterfield @ Tic Tocs Tech
Author-email: tom@tictocs.com
License: UNKNOWN
Project-URL: Bug Reports, https://github.com/tictocs/markdown-google-map/issues
Project-URL: Source, https://github.com/tictocs/markdown-google-map/
Platform: UNKNOWN
Classifier: Intended Audience :: Developers
Classifier: Topic :: Software Development :: Build Tools
Classifier: License :: OSI Approved :: MIT License
Classifier: Programming Language :: Python :: 3
Provides-Extra: dev
Requires-Dist: markdown (>=2.6.11)
Provides-Extra: dev
Requires-Dist: beautifulsoup4; extra == 'dev'
